setup.py
writerscript/__init__.py
writerscript/cli.py
writerscript/generator.py
writerscript/interpreter.py
writerscript/translator.py
writerscript-0.4.0.dist-info/LICENSE
writerscript-0.4.0.dist-info/METADATA
writerscript-0.4.0.dist-info/WHEEL
writerscript-0.4.0.dist-info/entry_points.txt
writerscript-0.4.0.dist-info/top_level.txt
writerscript-0.4.0.dist-info/RECORD
