Metadata-Version: 2.1
Name: writerscript
Version: 0.4.0
Summary: A word count based Esoteric Programming Language based on logic of BrainFuck
Home-page: https://github.com/Saket-Upadhyay/WriterScript
Author: Saket Upadhyay
Author-email: x64mayhem@gmail.com
License: MIT
Keywords: esoteric programming language brainfuck x64mayhem writerscript
Platform: UNKNOWN
Classifier: Development Status :: 4 - Beta
Classifier: Environment :: Console
Classifier: Intended Audience :: Developers
Classifier: Intended Audience :: Science/Research
Classifier: License :: OSI Approved :: MIT License
Classifier: Operating System :: OS Independent
Classifier: Programming Language :: Python
Classifier: Programming Language :: Python :: 2
Classifier: Programming Language :: Python :: 2.6
Classifier: Programming Language :: Python :: 2.7
Classifier: Programming Language :: Python :: 3
Classifier: Programming Language :: Python :: 3.4
Classifier: Programming Language :: Python :: 3.5
Classifier: Programming Language :: Python :: 3.6
Classifier: Programming Language :: Python :: 3.7
Classifier: Programming Language :: Python :: Implementation :: PyPy
Requires-Dist: ply
